datasette_geojson/__init__.py
datasette_geojson-0.4.0.dist-info/METADATA
datasette_geojson-0.4.0.dist-info/WHEEL
datasette_geojson-0.4.0.dist-info/entry_points.txt
datasette_geojson-0.4.0.dist-info/top_level.txt
datasette_geojson-0.4.0.dist-info/RECORD
