Metadata-Version: 2.1
Name: datasette-geojson
Version: 0.4.0
Summary: Add GeoJSON as an output option
Home-page: https://github.com/eyeseast/datasette-geojson
Author: Chris Amico
License: Apache License, Version 2.0
Project-URL: Issues, https://github.com/eyeseast/datasette-geojson/issues
Project-URL: CI, https://github.com/eyeseast/datasette-geojson/actions
Project-URL: Changelog, https://github.com/eyeseast/datasette-geojson/releases
Requires-Python: >=3.7
Requires-Dist: datasette
Requires-Dist: geojson
Provides-Extra: test
Requires-Dist: pytest ; extra == 'test'
Requires-Dist: pytest-asyncio ; extra == 'test'
Requires-Dist: geojson-to-sqlite ; extra == 'test'
